pyferret/__init__.py
pyferret/abstract.py
pyferret/helpers.py
pyferret/maybe.py
pyferret/py.typed
pyferret/result.py
pyferret-0.2.1.dist-info/METADATA
pyferret-0.2.1.dist-info/WHEEL
pyferret-0.2.1.dist-info/RECORD
