Metadata-Version: 2.1
Name: pyferret
Version: 0.2.1
Summary: Functional programming tools for Python
Author: archds
Author-email: dsalekseev11@gmail.com
Requires-Python: >=3.11,<4.0
Classifier: Programming Language :: Python :: 3
Classifier: Programming Language :: Python :: 3.11
